[
  {
    "keyword": "adhd planner printable",
    "etsy_listings": 34763,
    "avg_price_usd": 8.81,
    "source": [
      "etsy"
    ],
    "score": null,
    "monthly_searches": 0,
    "trend_direction": "stable",
    "competition": "high",
    "reddit_signal": false
  },
  {
    "keyword": "budget tracker pdf",
    "etsy_listings": 36084,
    "avg_price_usd": 5.09,
    "source": [
      "etsy"
    ],
    "score": null,
    "monthly_searches": 0,
    "trend_direction": "stable",
    "competition": "high",
    "reddit_signal": false
  },
  {
    "keyword": "notion template",
    "etsy_listings": 21016,
    "avg_price_usd": 89.76,
    "source": [
      "etsy"
    ],
    "score": null,
    "monthly_searches": 0,
    "trend_direction": "stable",
    "competition": "high",
    "reddit_signal": false
  },
  {
    "keyword": "ai prompt pack",
    "etsy_listings": 2696,
    "avg_price_usd": 14.65,
    "source": [
      "etsy"
    ],
    "score": null,
    "monthly_searches": 0,
    "trend_direction": "stable",
    "competition": "high",
    "reddit_signal": false
  },
  {
    "keyword": "habit tracker printable",
    "etsy_listings": 58614,
    "avg_price_usd": 4.3,
    "source": [
      "etsy"
    ],
    "score": null,
    "monthly_searches": 0,
    "trend_direction": "stable",
    "competition": "high",
    "reddit_signal": false
  },
  {
    "keyword": "productivity planner",
    "etsy_listings": 99830,
    "avg_price_usd": 6.74,
    "source": [
      "etsy"
    ],
    "score": null,
    "monthly_searches": 0,
    "trend_direction": "stable",
    "competition": "high",
    "reddit_signal": false
  },
  {
    "keyword": "weekly planner printable",
    "etsy_listings": 129825,
    "avg_price_usd": 6.17,
    "source": [
      "etsy"
    ],
    "score": null,
    "monthly_searches": 0,
    "trend_direction": "stable",
    "competition": "high",
    "reddit_signal": false
  },
  {
    "keyword": "social media caption pack",
    "etsy_listings": 611,
    "avg_price_usd": 10.39,
    "source": [
      "etsy"
    ],
    "score": null,
    "monthly_searches": 0,
    "trend_direction": "stable",
    "competition": "medium",
    "reddit_signal": false
  },
  {
    "keyword": "resume template",
    "etsy_listings": 38640,
    "avg_price_usd": 7.34,
    "source": [
      "etsy"
    ],
    "score": null,
    "monthly_searches": 0,
    "trend_direction": "stable",
    "competition": "high",
    "reddit_signal": false
  },
  {
    "keyword": "party printable",
    "etsy_listings": 3563728,
    "avg_price_usd": 8.84,
    "source": [
      "etsy"
    ],
    "score": null,
    "monthly_searches": 0,
    "trend_direction": "stable",
    "competition": "high",
    "reddit_signal": false
  }
]